roxieinterfaces/__init__.py
roxieinterfaces/ansys.py
roxieinterfaces/geom/__init__.py
roxieinterfaces/geom/_cadquery.py
roxieinterfaces/geom/geom.py
roxieinterfaces/geom/geom_script.py
roxieinterfaces/geom/math_tools.py
roxieinterfaces/mesh/__init__.py
roxieinterfaces/mesh/meshes.py
roxieinterfaces-0.5.0.dist-info/METADATA
roxieinterfaces-0.5.0.dist-info/WHEEL
roxieinterfaces-0.5.0.dist-info/entry_points.txt
roxieinterfaces-0.5.0.dist-info/licenses/LICENSES/BSD-4-Clause.txt
roxieinterfaces-0.5.0.dist-info/RECORD
