Metadata-Version: 2.4
Name: roxieinterfaces
Version: 0.5.0
Summary: Interfaces implementation to roxie
License-Expression: BSD-4-Clause
License-File: LICENSES/BSD-4-Clause.txt
Author: Matthias Bonora
Author-email: matthias.bonora@cern.ch
Requires-Python: >=3.11,<3.13
Classifier: Intended Audience :: Education
Classifier: License :: OSI Approved :: BSD License
Classifier: Operating System :: OS Independent
Classifier: Programming Language :: Python :: 3
Classifier: Programming Language :: Python :: 3.11
Classifier: Programming Language :: Python :: 3.12
Requires-Dist: cadquery (>=2.6.0,<3.0.0)
Requires-Dist: gmsh (>=4.11.1,<5.0.0)
Requires-Dist: pyvista (>=0.44,<0.45)
Requires-Dist: roxie-api (>=0.4.4,<0.5.0)
Requires-Dist: scipy (>=1.16,<2.0)
Project-URL: Documentation, https://roxie-interfaces.docs.cern.ch/
Project-URL: Homepage, https://roxie.docs.cern.ch/
Project-URL: Repository, https://gitlab.cern.ch/te-msc-mm/templates/python-package-template
